README.rst
secs
secs.py
setup.cfg
setup.py
secs.egg-info/PKG-INFO
secs.egg-info/SOURCES.txt
secs.egg-info/dependency_links.txt
secs.egg-info/entry_points.txt
secs.egg-info/top_level.txt