Metadata-Version: 1.1
Name: secs
Version: 0.2.0
Summary: Simple encrypted containers
Home-page: https://github.com/dhagrow/secs
Author: Miguel Turner
Author-email: cymrow@gmail.com
License: MIT
Keywords: luks,container,encryption,crypto,crytography
Platform: UNKNOWN
Classifier: Development Status :: 4 - Beta
Classifier: Environment :: Console
Classifier: Intended Audience :: End Users/Desktop
Classifier: License :: OSI Approved :: MIT License
Classifier: Operating System :: POSIX :: Linux
Classifier: Programming Language :: Python :: 2
Classifier: Programming Language :: Python :: 2.7
Classifier: Programming Language :: Python :: 3
Classifier: Programming Language :: Python :: 3.2
Classifier: Programming Language :: Python :: 3.3
Classifier: Programming Language :: Python :: 3.4
Classifier: Programming Language :: Python :: 3.5
Classifier: Programming Language :: Python :: 3.6
Classifier: Topic :: Security :: Cryptography
Classifier: Topic :: System :: Filesystems
Classifier: Topic :: Utilities
